lmclient/__init__.py
lmclient/cache.py
lmclient/chat_engine.py
lmclient/completion_engine.py
lmclient/exceptions.py
lmclient/models/__init__.py
lmclient/models/azure.py
lmclient/models/baichuan.py
lmclient/models/base.py
lmclient/models/http.py
lmclient/models/hunyuan.py
lmclient/models/minimax.py
lmclient/models/minimax_pro.py
lmclient/models/openai.py
lmclient/models/wenxin.py
lmclient/models/zhipu.py
lmclient/parser.py
lmclient/types.py
lmclient/utils.py
lmclient/version.py
lmclient_core-0.8.4.dist-info/LICENSE
lmclient_core-0.8.4.dist-info/METADATA
lmclient_core-0.8.4.dist-info/WHEEL
lmclient_core-0.8.4.dist-info/RECORD
