Metadata-Version: 2.1
Name: lmclient-core
Version: 0.8.4
Summary: LM Async Client, openai client, azure openai client ...
Home-page: https://github.com/wangyuxinwhy/lmclient
License: Apache-2.0
Keywords: lmclient,openai,azure,async
Author: wangyuxin
Author-email: wangyuxin@mokahr.com
Requires-Python: >=3.8,<4.0
Classifier: License :: OSI Approved :: Apache Software License
Classifier: Programming Language :: Python :: 3
Classifier: Programming Language :: Python :: 3.8
Classifier: Programming Language :: Python :: 3.9
Classifier: Programming Language :: Python :: 3.10
Classifier: Programming Language :: Python :: 3.11
Requires-Dist: anyio (<4.0.0)
Requires-Dist: asyncer (==0.0.2)
Requires-Dist: cachetools (>=5.3.1,<6.0.0)
Requires-Dist: diskcache (>=5.6.1,<6.0.0)
Requires-Dist: docstring-parser (>=0.15,<0.16)
Requires-Dist: httpx (>=0.24.1,<0.25.0)
Requires-Dist: pydantic (>1.0)
Requires-Dist: pyjwt (>=2.8.0,<3.0.0)
Requires-Dist: tenacity (>=8.2.2,<9.0.0)
Requires-Dist: tqdm (>=4.66.1,<5.0.0)
Requires-Dist: typing-extensions (>=4.6.2,<5.0.0)
Requires-Dist: websocket-client (>=1.6.1,<2.0.0)
Project-URL: Repository, https://github.com/wangyuxinwhy/lmclient
